relaton/__init__.py
relaton/py.typed
relaton/util.py
relaton/models/__init__.py
relaton/models/bibdata.py
relaton/models/bibitemlocality.py
relaton/models/contacts.py
relaton/models/copyrights.py
relaton/models/dates.py
relaton/models/links.py
relaton/models/orgs.py
relaton/models/people.py
relaton/models/strings.py
relaton/serializers/__init__.py
relaton/serializers/types.py
relaton/serializers/bibxml/__init__.py
relaton/serializers/bibxml/abstracts.py
relaton/serializers/bibxml/anchor.py
relaton/serializers/bibxml/authors.py
relaton/serializers/bibxml/reference.py
relaton/serializers/bibxml/series.py
relaton/serializers/bibxml/target.py
relaton/tests/__init__.py
relaton/tests/test_serializers.py
relaton/tests/validate_remote_data_against_models.py
relaton-0.2.33.dist-info/LICENSE
relaton-0.2.33.dist-info/METADATA
relaton-0.2.33.dist-info/WHEEL
relaton-0.2.33.dist-info/top_level.txt
relaton-0.2.33.dist-info/RECORD
