Metadata-Version: 2.1
Name: relaton
Version: 0.2.33
Summary: Library for working with Relaton bibliographic data models in Python. Provides Pydantic models and dataclasses, as well as parsers and serializers.
Home-page: http://github.com/relaton/relaton-py/
Author: Ribose Inc.
Author-email: open@ribose.com
License: BSD 2-clause
Keywords: Relaton,bibliographic data,bibliography,Pydantic,dataclasses
Platform: UNKNOWN
Classifier: Programming Language :: Python :: 3.10
Classifier: Development Status :: 2 - Pre-Alpha
Classifier: Intended Audience :: Developers
Classifier: Natural Language :: English
Classifier: License :: OSI Approved :: MIT License
Classifier: Operating System :: POSIX
License-File: LICENSE
